Metadata-Version: 1.1
Name: django-ajax-forms-mega
Version: 0.2.13
Summary: Provides support for doing validation using Ajax(currently with jQuery) using your existing Django forms.
Home-page: https://github.com/chrisspen/django-ajax-forms
Author: Chris Spencer
Author-email: chrisspen@gmail.com
License: UNKNOWN
Platform: UNKNOWN
Classifier: Development Status :: 3 - Alpha
Classifier: Environment :: Web Environment
Classifier: Intended Audience :: Developers
Classifier: License :: OSI Approved :: BSD License
Classifier: Operating System :: OS Independent
Classifier: Programming Language :: Python
Classifier: Framework :: Django
